v2sim/__init__.py
v2sim/sim_core.py
v2sim/gui/com_no_vx.py
v2sim/gui/common.py
v2sim/gui/evtq.py
v2sim/gui/langhelper.py
v2sim/gui/v2sim.png
v2sim/gui/cmpbox/__init__.py
v2sim/gui/cmpbox/_lang/en_US.lang
v2sim/gui/cmpbox/_lang/zh_CN.lang
v2sim/gui/mainbox/__init__.py
v2sim/gui/mainbox/cscsveditor.py
v2sim/gui/mainbox/cseditor.py
v2sim/gui/mainbox/loadingbox.py
v2sim/gui/mainbox/plugin.py
v2sim/gui/mainbox/utils.py
v2sim/gui/mainbox/_lang/en.lang
v2sim/gui/mainbox/_lang/zh_CN.lang
v2sim/gui/mainbox/controls/__init__.py
v2sim/gui/mainbox/controls/lipad.py
v2sim/gui/mainbox/controls/network.py
v2sim/gui/mainbox/controls/pdfe.py
v2sim/gui/mainbox/controls/prope.py
v2sim/gui/mainbox/controls/rle.py
v2sim/gui/mainbox/controls/scrtv.py
v2sim/gui/mainbox/controls/sfe.py
v2sim/gui/mainbox/controls/sid.py
v2sim/gui/mainbox/controls/utils.py
v2sim/gui/mainbox/controls/_lang/en.lang
v2sim/gui/mainbox/controls/_lang/zh_CN.lang
v2sim/gui/parabox/__init__.py
v2sim/gui/parabox/lgb.py
v2sim/gui/parabox/pareditor.py
v2sim/gui/parabox/utils.py
v2sim/gui/parabox/_lang/en.lang
v2sim/gui/parabox/_lang/zh_CN.lang
v2sim/gui/plgbox/__init__.py
v2sim/gui/plgbox/_lang/en_US.lang
v2sim/gui/plgbox/_lang/zh_CN.lang
v2sim/gui/progbox/__init__.py
v2sim/gui/viewerbox/__init__.py
v2sim/gui/viewerbox/gridpage.py
v2sim/gui/viewerbox/optbox.py
v2sim/gui/viewerbox/plotpad.py
v2sim/gui/viewerbox/plotpage.py
v2sim/gui/viewerbox/srd.py
v2sim/gui/viewerbox/statepage.py
v2sim/gui/viewerbox/trips.py
v2sim/gui/viewerbox/_lang/en_US.lang
v2sim/gui/viewerbox/_lang/zh_CN.lang
v2sim/gui/welcomebox/__init__.py
v2sim/gui/welcomebox/v2sim.png
v2sim/gui/welcomebox/_lang/en_US.lang
v2sim/gui/welcomebox/_lang/zh_CN.lang
v2sim/locale/__init__.py
v2sim/locale/lang.py
v2sim/locale/zh_CN.py
v2sim/osmhelper/__init__.py
v2sim/osmhelper/osmBuild.py
v2sim/osmhelper/osmGet.py
v2sim/osmhelper/osmWebWizard.py
v2sim/osmhelper/ptlines2flows.py
v2sim/osmhelper/readme.md
v2sim/osmhelper/tileGet.py
v2sim-1.3.0rc2.dist-info/METADATA
v2sim-1.3.0rc2.dist-info/WHEEL
v2sim-1.3.0rc2.dist-info/entry_points.txt
v2sim-1.3.0rc2.dist-info/licenses/LICENSE
v2sim-1.3.0rc2.dist-info/RECORD
