Metadata-Version: 2.4
Name: v2sim
Version: 1.3.0rc2
Summary: V2Sim: An Open-Source Microscopic V2G Simulation Platform in Urban Power and Transportation Network
Project-URL: Homepage, https://github.com/fmy-xfk/v2sim
Project-URL: Documentation, https://github.com/fmy-xfk/v2sim/wiki
Project-URL: Repository, https://github.com/fmy-xfk/v2sim.git
Project-URL: Issues, https://github.com/fmy-xfk/v2sim/issues
License-Expression: BSD-3-Clause
License-File: LICENSE
Requires-Python: >=3.8
Requires-Dist: feasytools>=0.1.4
Requires-Dist: fpowerkit>=0.3.4
Requires-Dist: libsumo
Requires-Dist: matplotlib
Requires-Dist: numba
Requires-Dist: numpy
Requires-Dist: pyproj
Requires-Dist: requests
Requires-Dist: scikit-learn
Provides-Extra: v2g
Requires-Dist: cvxpy; extra == 'v2g'
Requires-Dist: ecos; extra == 'v2g'
